ncep_data_req/__init__.py
ncep_data_req/core.py
ncep_data_req-0.1.2.3.dist-info/METADATA
ncep_data_req-0.1.2.3.dist-info/WHEEL
ncep_data_req-0.1.2.3.dist-info/top_level.txt
ncep_data_req-0.1.2.3.dist-info/RECORD
