Metadata-Version: 2.4
Name: ncep_data_req
Version: 0.1.2.3
Summary: Download and process NCEP GFS 0.25° data via ASCII interface
Author: Subhrajit Rath
Author-email: subhrajitrath17@gmail.com
Classifier: Programming Language :: Python :: 3
Classifier: Operating System :: OS Independent
Requires-Python: >=3.7
Requires-Dist: pandas
Requires-Dist: numpy
Requires-Dist: xarray
Requires-Dist: requests
Requires-Dist: matplotlib
Dynamic: author
Dynamic: author-email
Dynamic: classifier
Dynamic: description
Dynamic: description-content-type
Dynamic: requires-dist
Dynamic: requires-python
Dynamic: summary
